<?xml version="1.0" encoding="utf-8"?>
<LanguageData>
  <!--The following translations were generated by https://www.deepl.com/-->
  <BmuS.ManuallyInfo>Manuell von der Workstation aus,</BmuS.ManuallyInfo>
  <BmuS.AutomaticInfo>Automatisch,</BmuS.AutomaticInfo>
  <BmuS.Automatic>Automatisch</BmuS.Automatic>
  <BmuS.Manual>Handbuch</BmuS.Manual>
  <BmuS.AutoOutbound>Automatisch ausgehend</BmuS.AutoOutbound>
  <BmuS.QualityMatters>Qualität ist wichtig</BmuS.QualityMatters>
  <BmuS.Registry>Registry</BmuS.Registry>
  <BmuS.RegistryEmpty>Das Register ist leer</BmuS.RegistryEmpty>
  <BmuS.RegistryFull>Das Register ist voll</BmuS.RegistryFull>
  <BmuS.BuildInRange>Baue eine {0} in ihrem Bereich.</BmuS.BuildInRange>
  <BmuS.NoAdditional>Keine weiteren {0} werden von diesem {1} verwaltet. Seine Registry ist voll.</BmuS.NoAdditional>
  <BmuS.ListTeleporter>Listen {0} Teleporter</BmuS.ListTeleporter>
  <BmuS.ListTeleporters>Listet {0} Teleporter auf</BmuS.ListTeleporters>
  <BmuS.CloseSpot>Close Spot ist leer, während Sie bestellen, um etwas wegzuschicken</BmuS.CloseSpot>
  <BmuS.AwaySpot>Der Platz in der Ferne ist leer, während du bestellst, um etwas zurückzubringen</BmuS.AwaySpot>
  <BmuS.OneOfTwo>Einer der beiden Plätze ist frei</BmuS.OneOfTwo>
  <BmuS.NothingToTeleport>Nichts zu teleportieren</BmuS.NothingToTeleport>
  <BmuS.BrowseRecords>{0} Datensätze durchsuchen</BmuS.BrowseRecords>
  <BmuS.RegistryTitle>| Arbeitsstation-Registrierung |</BmuS.RegistryTitle>
  <BmuS.Records>{0} Datensätze.</BmuS.Records>
  <BmuS.Empty>Leere.</BmuS.Empty>
  <BmuS.OrphanSpot>Verwaistes Fleckchen!</BmuS.OrphanSpot>
  <BmuS.Tip>Tipp</BmuS.Tip>
  <BmuS.Tips>Tipps</BmuS.Tips>
  <BmuS.BuildaInRange>- Bauen Sie eine {0} im Bereich {1}.</BmuS.BuildaInRange>
  <BmuS.SelectColonist>- Wählen Sie einen Kolonisten und klicken Sie dann mit der rechten Maustaste auf das verwaiste {0}, um es mit einem {1} zu verbinden.</BmuS.SelectColonist>
  <BmuS.QualityLog>Registry-Kapazität: {0}
Bereich: {1}
Assistentenbereich: {2}</BmuS.QualityLog>
  <BmuS.EmptyRegistry>Leere Registry.</BmuS.EmptyRegistry>
  <BmuS.CheckRegistryRecord>Check registry({0} record).</BmuS.CheckRegistryRecord>
  <BmuS.CheckRegistryRecords>Registrierung prüfen ({0} Datensätze).</BmuS.CheckRegistryRecords>
  <BmuS.Roger>Roger</BmuS.Roger>
  <BmuS.SayWhat>Was sagen Sie?</BmuS.SayWhat>
  <BmuS.Nothing>Nichts</BmuS.Nothing>
  <BmuS.ItemKg>{0} Posten</BmuS.ItemKg>
  <BmuS.ItemsKg>{0} Artikel</BmuS.ItemsKg>
  <BmuS.WarmUp>Aufwärmen: {0} - {1}</BmuS.WarmUp>
  <BmuS.NoPower>Keine Leistung</BmuS.NoPower>
  <BmuS.NoFacility>Keine Einrichtung</BmuS.NoFacility>
  <BmuS.NoPoweredFacility>Keine elektrische Anlage</BmuS.NoPoweredFacility>
  <BmuS.CooldownPercent>Abklingzeit {0} - {1}</BmuS.CooldownPercent>
  <BmuS.LinkedCooldownPercent>Abklingzeit der verbundenen Stelle {0} - {1}</BmuS.LinkedCooldownPercent>
  <BmuS.Orphan>Waisenkind.</BmuS.Orphan>
  <BmuS.NotAValidSpot>{0} ist kein gültiger tp-Spot, sondern ein {1}</BmuS.NotAValidSpot>
  <BmuS.Power>Leistung: {0}</BmuS.Power>
  <BmuS.Facility>Einrichtung: {0}</BmuS.Facility>
  <BmuS.Found>Gefunden:</BmuS.Found>
  <BmuS.FacilityPower>FacilityPower: {0}</BmuS.FacilityPower>
  <BmuS.BelongsTo>Gehört zu</BmuS.BelongsTo>
  <BmuS.Chillin>Chillin</BmuS.Chillin>
  <BmuS.Overweight>Übergewicht</BmuS.Overweight>
  <BmuS.NothingToDo>nichts zu tun</BmuS.NothingToDo>
  <BmuS.ReadyToTp>bereit zu tp N:{0}:{1}</BmuS.ReadyToTp>
  <BmuS.Unlink>Unlink</BmuS.Unlink>
  <BmuS.UnlinkTT>Klicken Sie mit der rechten Maustaste auf einen Kolonisten, um ihn mit einem anderen Tp-Spot zu verbinden.</BmuS.UnlinkTT>
  <BmuS.UnlinkTTExpanded>Verknüpft mit {0}
{1} {2} {3}
Zum Aufheben der Verknüpfung anklicken.</BmuS.UnlinkTTExpanded>
  <BmuS.Browse>Wege durchsuchen</BmuS.Browse>
  <BmuS.Current>Strom : {0}</BmuS.Current>
  <BmuS.ClickToChange>Klicken Sie, um zu {0} zu wechseln.</BmuS.ClickToChange>
  <BmuS.SetAutomatic>automatisch einstellen</BmuS.SetAutomatic>
  <BmuS.OnePowered>Mindestens eine der beiden Stellen muss mit Strom versorgt werden.</BmuS.OnePowered>
  <BmuS.CannotTargetItself>{0} kann nicht auf sich selbst zielen</BmuS.CannotTargetItself>
  <BmuS.OutOfRange>{0} liegt außerhalb des Bereichs (Abstand : {1}, max : {2})</BmuS.OutOfRange>
  <BmuS.WasWasntLinked>{0} {1}{2} war {3}verbunden mit {4}{5}</BmuS.WasWasntLinked>
  <BmuS.Not>nicht</BmuS.Not>
  <BmuS.LinkedSpot>(Verlinkte Stelle)</BmuS.LinkedSpot>
  <BmuS.PowerRequired>Erforderliche Leistung{0}</BmuS.PowerRequired>
  <BmuS.FacilityRequired>Einrichtung erforderlich{0}</BmuS.FacilityRequired>
  <BmuS.FacilityPowerRequired>Elektrische Anlage erforderlich{0}</BmuS.FacilityPowerRequired>
  <BmuS.ExcessWeight>Überschüssiges Gewicht festgestellt{0}</BmuS.ExcessWeight>
  <BmuS.Cooldown>Abklingzeit läuft{0}</BmuS.Cooldown>
  <BmuS.OrphanSpotIs>Verwaister Fleck{0}</BmuS.OrphanSpotIs>
  <BmuS.ShouldNotHappen>Dies sollte nicht passieren{0}</BmuS.ShouldNotHappen>
</LanguageData>